MANIFEST.in
README.rst
setup.py
collective/__init__.py
collective.tinymceplugins.imagebrowser.egg-info/PKG-INFO
collective.tinymceplugins.imagebrowser.egg-info/SOURCES.txt
collective.tinymceplugins.imagebrowser.egg-info/dependency_links.txt
collective.tinymceplugins.imagebrowser.egg-info/entry_points.txt
collective.tinymceplugins.imagebrowser.egg-info/namespace_packages.txt
collective.tinymceplugins.imagebrowser.egg-info/not-zip-safe
collective.tinymceplugins.imagebrowser.egg-info/requires.txt
collective.tinymceplugins.imagebrowser.egg-info/top_level.txt
collective/tinymceplugins/__init__.py
collective/tinymceplugins/imagebrowser/__init__.py
collective/tinymceplugins/imagebrowser/configure.zcml
collective/tinymceplugins/imagebrowser/interfaces.py
collective/tinymceplugins/imagebrowser/testing.py
collective/tinymceplugins/imagebrowser/upgrades.py
collective/tinymceplugins/imagebrowser/browser/__init__.py
collective/tinymceplugins/imagebrowser/browser/adapter.py
collective/tinymceplugins/imagebrowser/browser/configure.zcml
collective/tinymceplugins/imagebrowser/browser/controlpanel.py
collective/tinymceplugins/imagebrowser/browser/imagebrowser_resources.py
collective/tinymceplugins/imagebrowser/browser/interfaces.py
collective/tinymceplugins/imagebrowser/locales/collective.tinymceplugins.imagebrowser.pot
collective/tinymceplugins/imagebrowser/locales/en/LC_MESSAGES/collective.tinymceplugins.imagebrowser.mo
collective/tinymceplugins/imagebrowser/locales/en/LC_MESSAGES/collective.tinymceplugins.imagebrowser.po
collective/tinymceplugins/imagebrowser/profiles/default/browserlayer.xml
collective/tinymceplugins/imagebrowser/profiles/default/collective.tinymceplugins.imagebrowser.txt
collective/tinymceplugins/imagebrowser/profiles/default/metadata.xml
collective/tinymceplugins/imagebrowser/profiles/default/registry.xml
collective/tinymceplugins/imagebrowser/profiles/default/skins.xml
collective/tinymceplugins/imagebrowser/profiles/default/tinymce.xml
collective/tinymceplugins/imagebrowser/profiles/to1beta3/controlpanel.xml
collective/tinymceplugins/imagebrowser/profiles/to1beta3/metadata.xml
collective/tinymceplugins/imagebrowser/skins/tinymce_plugin_imagebrowser/ploneimagebrowser/editor_plugin.js
collective/tinymceplugins/imagebrowser/skins/tinymce_plugin_imagebrowser/ploneimagebrowser/ploneimage.htm.pt
collective/tinymceplugins/imagebrowser/skins/tinymce_plugin_imagebrowser/ploneimagebrowser/css/ploneimage.css.dtml
