Metadata-Version: 1.0
Name: collective.tinymceplugins.imagebrowser
Version: 1.0b6
Summary: A TinyMCE plugin to provide thumbnail image browsing and a      ressource library
Home-page: https://github.com/collective/collective.tinymceplugins.imagebrowser
Author: Joscha Krutzki
Author-email: joka@jokasis.de
License: GPL
Keywords: tinymce plugin thumbnail image browsing ressource library
Platform: UNKNOWN
Classifier: Programming Language :: Python
Classifier: Framework :: Plone
Classifier: Programming Language :: JavaScript
